{"Volumes": {"Volume4": {"Issue2": {"Article No.: 8": [], "Article No.: 11": [], "Article No.: 7": [], "Article No.: 10": [], "Article No.: 9": []}, "Issue1": {"Article No.: 6": [], "Article No.: 3": [], "Article No.: 5": [], "Article No.: 2": [], "Article No.: 1": [], "Article No.: 4": []}, "Issue3": {"Article No.: 14": [], "Article No.: 13": [], "Article No.: 15": []}}, "Volume3": {"Issue2": {"Article No.: 8": [{"Country": null, "Affiliation": null, "Name": "Tuomas Sandholm"}], "Article No.: 10": [], "Article No.: 9": [], "Article No.: 12": [], "Article No.: 11": [], "Article No.: 7": []}, "Issue1": {"Article No.: 6": [], "Article No.: 3": [{"Country": null, "Affiliation": null, "Name": "David Kurokawa "}, {"Country": null, "Affiliation": null, "Name": "Ariel D. Procaccia "}], "Article No.: 5": [], "Article No.: 2": [], "Article No.: 1": [], "Article No.: 4": []}, "Issue4": {"Article No.: 19": [], "Article No.: 20": [], "Article No.: 25": [], "Article No.: 18": [], "Article No.: 21": [], "Article No.: 23": [], "Article No.: 24": [], "Article No.: 17": [], "Article No.: 22": [], "Article No.: 26": []}, "Issue3": {"Article No.: 14": [], "Article No.: 13": [], "Article No.: 16": [], "Article No.: 15": []}}, "Volume2": {"Issue2": {"Article No.: 8": [], "Article No.: 7": [], "Article No.: 5": [], "Article No.: 6": []}, "Issue1": {"Article No.: 3": [{"Country": null, "Affiliation": null, "Name": "Fabrice Talla Nobibon "}, {"Country": null, "Affiliation": null, "Name": "Bart Smeulders "}, {"Country": null, "Affiliation": null, "Name": "Frits C. Spieksma"}], "Article No.: 1": [], "Article No.: 4": [], "Article No.: 2": []}, "Issue4": {"Article No.: 14": [], "Article No.: 13": [], "Article No.: 16": [{"Country": "argentina", "Affiliation": null, "Name": "Piotr L. Szczepanski "}, {"Country": "argentina", "Affiliation": null, "Name": "Aleksy Barcz "}, {"Country": "argentina", "Affiliation": null, "Name": "Tomasz P. Michalak "}, {"Country": null, "Affiliation": null, "Name": "Talal Rahwan "}, {"Country": null, "Affiliation": null, "Name": "Tomasz P. Michalak "}, {"Country": null, "Affiliation": null, "Name": "Michael Wooldridge "}, {"Country": null, "Affiliation": null, "Name": "Nicholas R. Jennings"}], "Article No.: 15": [], "Article No.: 17": []}, "Issue3": {"Article No.: 11": [], "Article No.: 9": [], "Article No.: 10": [], "Article No.: 12": []}}, "Volume1": {"Issue2": {"Article No.: 8": [], "Article No.: 10": [], "Article No.: 7": [], "Article No.: 5": [], "Article No.: 9": [], "Article No.: 12": [{"Country": null, "Affiliation": null, "Name": "Xi Alice Gao "}, {"Country": null, "Affiliation": null, "Name": "Jie Zhang "}, {"Country": null, "Affiliation": null, "Name": "Yiling Chen"}, {"Country": null, "Affiliation": null, "Name": "Hoda Heidari "}, {"Country": null, "Affiliation": null, "Name": "Sebastien Lahaie "}, {"Country": null, "Affiliation": null, "Name": "David M. Pennock "}, {"Country": null, "Affiliation": null, "Name": "Yiling Chen "}, {"Country": null, "Affiliation": null, "Name": "Ian A. Kash "}, {"Country": null, "Affiliation": null, "Name": "Jacob D. Abernethy "}, {"Country": null, "Affiliation": null, "Name": "Rafael M. Frongillo "}, {"Country": null, "Affiliation": null, "Name": "Jacob D. Abernethy "}, {"Country": null, "Affiliation": null, "Name": "Rafael M. Frongillo "}], "Article No.: 11": [], "Article No.: 13": [{"Country": "argentina", "Affiliation": null, "Name": "Minming Li "}, {"Country": "argentina", "Affiliation": null, "Name": "Jialin Zhang "}, {"Country": "argentina", "Affiliation": null, "Name": "Qiang Zhang"}], "Article No.: 6": [{"Country": "france", "Affiliation": null, "Name": "Othon Michail "}, {"Country": "france", "Affiliation": null, "Name": "Paul G. Spirakis"}]}, "Issue1": {"Article No.: 3": [{"Country": null, "Affiliation": null, "Name": "Hajime Mizuyama "}, {"Country": null, "Affiliation": null, "Name": "Eiji Miyashita"}, {"Country": null, "Affiliation": null, "Name": "Arpita Ghosh "}, {"Country": null, "Affiliation": null, "Name": "Patrick Hummel"}], "Article No.: 1": [], "Article No.: 4": [{"Country": null, "Affiliation": null, "Name": "Victor Naroditskiy "}, {"Country": null, "Affiliation": null, "Name": "Sofia Ceppi "}, {"Country": null, "Affiliation": null, "Name": "Valentin Robu "}, {"Country": null, "Affiliation": null, "Name": "Nicholas R. Jennings"}, {"Country": null, "Affiliation": null, "Name": "Victor Naroditskiy "}, {"Country": null, "Affiliation": null, "Name": "Mingyu Guo "}, {"Country": null, "Affiliation": null, "Name": "Lachlan Dufton "}, {"Country": null, "Affiliation": null, "Name": "Maria Polukarov "}, {"Country": null, "Affiliation": null, "Name": "Nicholas R. Jennings"}, {"Country": "canada", "Affiliation": null, "Name": "Lachlan Dufton "}, {"Country": "canada", "Affiliation": null, "Name": "Victor Naroditskiy "}, {"Country": "canada", "Affiliation": null, "Name": "Maria Polukarov "}, {"Country": "canada", "Affiliation": null, "Name": "Nicholas R. Jennings"}], "Article No.: 2": []}, "Issue4": {"Article No.: 19": [{"Country": null, "Affiliation": null, "Name": "L. Becchetti "}, {"Country": null, "Affiliation": null, "Name": "A. Clementi "}, {"Country": null, "Affiliation": null, "Name": "E. Natale "}, {"Country": null, "Affiliation": null, "Name": "F. Pasquale "}, {"Country": null, "Affiliation": null, "Name": "L. Trevisan"}], "Article No.: 20": [], "Article No.: 18": [{"Country": "turkey", "Affiliation": null, "Name": "Paolo Serafino"}, {"Country": "israel", "Affiliation": null, "Name": "Simina Br\u00e2nzei "}, {"Country": "israel", "Affiliation": null, "Name": "Ariel D. Procaccia"}], "Article No.: 21": []}, "Issue3": {"Article No.: 14": [], "Article No.: 16": [{"Country": null, "Affiliation": null, "Name": "Ioannis A. Moschakis "}, {"Country": null, "Affiliation": null, "Name": "Helen D. Karatza"}, {"Country": null, "Affiliation": null, "Name": "Orna Agmon Ben-Yehuda "}, {"Country": null, "Affiliation": null, "Name": "Muli Ben-Yehuda "}, {"Country": null, "Affiliation": null, "Name": "Assaf Schuster "}, {"Country": null, "Affiliation": null, "Name": "Dan Tsafrir"}, {"Country": "australia", "Affiliation": null, "Name": "Dalia Kaulakien\u0117 "}, {"Country": "australia", "Affiliation": null, "Name": "Christian Thomsen "}, {"Country": "australia", "Affiliation": null, "Name": "Torben Bach Pedersen "}, {"Country": "australia", "Affiliation": null, "Name": "Ugur \u00c7etintemel "}, {"Country": "australia", "Affiliation": null, "Name": "Tim Kraska"}, {"Country": null, "Affiliation": null, "Name": "Yifan Gong "}, {"Country": null, "Affiliation": null, "Name": "Bingsheng He "}, {"Country": null, "Affiliation": null, "Name": "Amelie Chi Zhou"}, {"Country": null, "Affiliation": null, "Name": "Fuhui Wu "}, {"Country": null, "Affiliation": null, "Name": "Qingbo Wu "}, {"Country": null, "Affiliation": null, "Name": "Yusong Tan"}], "Article No.: 15": [], "Article No.: 17": [{"Country": null, "Affiliation": null, "Name": "Chen Hajaj "}, {"Country": null, "Affiliation": null, "Name": "David Sarne"}, {"Country": null, "Affiliation": null, "Name": "Avshalom Elmalech "}, {"Country": null, "Affiliation": null, "Name": "David Sarne "}, {"Country": null, "Affiliation": null, "Name": "Barbara J. Grosz"}]}}}}